pyscsi/__init__.py
pyscsi/pyiscsi/__init__.py
pyscsi/pyiscsi/iscsi_device.py
pyscsi/pyscsi/__init__.py
pyscsi/pyscsi/scsi.py
pyscsi/pyscsi/scsi_cdb_exchangemedium.py
pyscsi/pyscsi/scsi_cdb_getlbastatus.py
pyscsi/pyscsi/scsi_cdb_initelementstatus.py
pyscsi/pyscsi/scsi_cdb_initelementstatuswithrange.py
pyscsi/pyscsi/scsi_cdb_inquiry.py
pyscsi/pyscsi/scsi_cdb_modesense10.py
pyscsi/pyscsi/scsi_cdb_modesense6.py
pyscsi/pyscsi/scsi_cdb_movemedium.py
pyscsi/pyscsi/scsi_cdb_openclose_exportimport_element.py
pyscsi/pyscsi/scsi_cdb_positiontoelement.py
pyscsi/pyscsi/scsi_cdb_preventallow_mediumremoval.py
pyscsi/pyscsi/scsi_cdb_read10.py
pyscsi/pyscsi/scsi_cdb_read12.py
pyscsi/pyscsi/scsi_cdb_read16.py
pyscsi/pyscsi/scsi_cdb_readcapacity10.py
pyscsi/pyscsi/scsi_cdb_readcapacity16.py
pyscsi/pyscsi/scsi_cdb_readcd.py
pyscsi/pyscsi/scsi_cdb_readelementstatus.py
pyscsi/pyscsi/scsi_cdb_report_luns.py
pyscsi/pyscsi/scsi_cdb_report_priority.py
pyscsi/pyscsi/scsi_cdb_testunitready.py
pyscsi/pyscsi/scsi_cdb_write10.py
pyscsi/pyscsi/scsi_cdb_write12.py
pyscsi/pyscsi/scsi_cdb_write16.py
pyscsi/pyscsi/scsi_cdb_writesame10.py
pyscsi/pyscsi/scsi_cdb_writesame16.py
pyscsi/pyscsi/scsi_command.py
pyscsi/pyscsi/scsi_device.py
pyscsi/pyscsi/scsi_enum_command.py
pyscsi/pyscsi/scsi_enum_getlbastatus.py
pyscsi/pyscsi/scsi_enum_inquiry.py
pyscsi/pyscsi/scsi_enum_modesense.py
pyscsi/pyscsi/scsi_enum_readcapacity16.py
pyscsi/pyscsi/scsi_enum_readelementstatus.py
pyscsi/pyscsi/scsi_exception.py
pyscsi/pyscsi/scsi_opcode.py
pyscsi/pyscsi/scsi_sense.py
pyscsi/utils/__init__.py
pyscsi/utils/converter.py
pyscsi/utils/enum.py
PYSCSI-2.1.0.dist-info/0BSD.txt
PYSCSI-2.1.0.dist-info/LGPL-2.1-or-later.txt
PYSCSI-2.1.0.dist-info/LICENSE
PYSCSI-2.1.0.dist-info/METADATA
PYSCSI-2.1.0.dist-info/MIT.txt
PYSCSI-2.1.0.dist-info/WHEEL
PYSCSI-2.1.0.dist-info/top_level.txt
PYSCSI-2.1.0.dist-info/RECORD
