Metadata-Version: 2.1
Name: PYSCSI
Version: 2.1.0
Summary: Module for calling SCSI devices from Python
Home-page: https://github.com/python-scsi/python-scsi
Maintainer: Markus Rosjat
Maintainer-email: markus.rosjat@gmail.com
License: LGPL-2.1
Keywords: scsi
Platform: UNKNOWN
Classifier: License :: OSI Approved :: GNU Lesser General Public License v2 (LGPLv2)
Classifier: License :: OSI Approved :: GNU Lesser General Public License v2 or later (LGPLv2+)
Classifier: Programming Language :: Python
Classifier: Programming Language :: Python :: 3
Requires-Python: ~=3.7
License-File: LICENSES/0BSD.txt
License-File: LICENSES/LGPL-2.1-or-later.txt
License-File: LICENSES/MIT.txt
License-File: LICENSE
Provides-Extra: dev
Requires-Dist: isort ; extra == 'dev'
Requires-Dist: mypy ; extra == 'dev'
Requires-Dist: pre-commit ; extra == 'dev'
Requires-Dist: pytest ; extra == 'dev'
Requires-Dist: pytest-mypy ; extra == 'dev'
Requires-Dist: setuptools (>=42) ; extra == 'dev'
Requires-Dist: setuptools-scm[toml] (>=3.4) ; extra == 'dev'
Requires-Dist: wheel ; extra == 'dev'
Provides-Extra: iscsi
Requires-Dist: cython-iscsi ; extra == 'iscsi'
Provides-Extra: sgio
Requires-Dist: cython-sgio (>=1.1.2) ; extra == 'sgio'
